SC2Spa/__init__.py
SC2Spa/__metadata__.py
SC2Spa/bm.py
SC2Spa/me.py
SC2Spa/pl.py
SC2Spa/pp.py
SC2Spa/sva.py
SC2Spa/tl.py
sc2spa-1.3.1.dist-info/LICENSE
sc2spa-1.3.1.dist-info/METADATA
sc2spa-1.3.1.dist-info/WHEEL
sc2spa-1.3.1.dist-info/top_level.txt
sc2spa-1.3.1.dist-info/RECORD
