Metadata-Version: 2.2
Name: SC2Spa
Version: 1.3.1
Summary: SC2Spa: a deep learning based approach to map transcriptome to spatial origins at cellular resolution
Author-email: "Linbu Liao, Won Lab" <linbu.liao@gmail.com>
License: BSD 3-Clause License
Project-URL: Homepage, https://github.com/linbuliao/SC2Spa
Project-URL: Bug Tracker, https://github.com/pypa/SC2Spa/issues
Classifier: Programming Language :: Python :: 3
Classifier: License :: OSI Approved :: BSD License
Classifier: Operating System :: OS Independent
Requires-Python: >=3.9
License-File: LICENSE
